stressy/__init__.py
stressy/stressy.py
stressy/utils.py
stressy-1.0.4.dist-info/LICENSE
stressy-1.0.4.dist-info/METADATA
stressy-1.0.4.dist-info/WHEEL
stressy-1.0.4.dist-info/entry_points.txt
stressy-1.0.4.dist-info/top_level.txt
stressy-1.0.4.dist-info/RECORD
