Metadata-Version: 2.1
Name: stressy
Version: 1.0.4
Summary: a tool to repeatedly run a command until failure
Author-email: Daniel Pauli <dapaulid@gmail.com>
License: The MIT License (MIT)
Project-URL: Homepage, https://github.com/dapaulid/stressy
Project-URL: Documentation, https://github.com/dapaulid/stressy
Project-URL: Repository, https://github.com/dapaulid/stressy.git
Project-URL: Bug Tracker, https://github.com/dapaulid/stressy/issues
Project-URL: Changelog, https://github.com/dapaulid/stressy
Keywords: testing,repeat,forever,retry,shell,cli
Classifier: Development Status :: 4 - Beta
Classifier: Natural Language :: English
Classifier: Operating System :: OS Independent
Classifier: Programming Language :: Python
Requires-Python: >=3.8
License-File: LICENSE
